{"cameraMode":{"drawMode":0,"name":"Shaded","section":"Shading Mode"},"sceneLighting":true,"audioPlay":false,"sceneViewState":{"showFog":true,"showMaterialUpdate":false,"showSkybox":true,"showFlares":true,"showImageEffects":true,"showParticleSystems":true},"in2DMode":false,"pivot":{"x":17.799304962158204,"y":3.062443733215332,"z":-2.1370716094970705},"rotation":{"x":-0.024380847811698915,"y":-0.706899881362915,"z":-0.02439667284488678,"w":0.7064722180366516},"size":10.637812614440918,"orthographic":false}